{
  "ComponentIndexes": {},
  "ControlUniqueIds": {
    "App": 1,
    "BeneficiaryInput": 39,
    "BeneficiaryLabel": 38,
    "Claim": 41,
    "ClaimBackArrow": 44,
    "ClaimButton": 110,
    "ClaimCreator": 114,
    "ClaimGallery": 46,
    "ClaimInfoLabel": 95,
    "ClaimNavigator": 8,
    "ClaimSeachtButton": 43,
    "ClaimSearchID": 45,
    "ClaimSpecBackArrow": 94,
    "ClaimSpecification": 93,
    "ClaimTitle": 42,
    "Contract": 22,
    "ContractBackArrow": 25,
    "ContractButton": 107,
    "ContractCreator": 112,
    "ContractGallery": 27,
    "ContractInfoLabel": 63,
    "ContractNavigator": 6,
    "ContractSearchButton": 24,
    "ContractSearchID": 26,
    "ContractsInput": 54,
    "ContractsLabel": 53,
    "ContractSpecBackArrow": 62,
    "ContractSpecification": 61,
    "ContractTitle": 23,
    "EntryScreen": 3,
    "EntryTitle": 4,
    "EntryTitle2": 106,
    "Gallery3": 97,
    "galleryTemplate2": 15,
    "galleryTemplate2_1": 86,
    "galleryTemplate2_2": 28,
    "galleryTemplate2_3": 47,
    "galleryTemplate3": 98,
    "HolderInput": 37,
    "HolderLabel": 36,
    "Image2": 16,
    "Image2_1": 87,
    "Image2_2": 29,
    "Image2_3": 48,
    "Image3": 99,
    "LoadMoreClaims": 55,
    "LoadMoreContracts": 40,
    "LoadMoreParties": 92,
    "LoadMoreProducts": 21,
    "NextArrow2": 18,
    "NextArrow2_1": 89,
    "NextArrow2_2": 31,
    "NextArrow2_3": 50,
    "NextArrow3": 101,
    "Party": 80,
    "PartyBackArrow": 83,
    "PartyButton": 108,
    "PartyCreator": 111,
    "PartyGallery": 85,
    "PartyIdentifierLabel": 60,
    "PartyIdentifierLabel_1": 67,
    "PartyIdentifierLabel_2": 73,
    "PartyIdentifierLabel_3": 74,
    "PartyIdentifierLabel_4": 68,
    "PartyIdentifierLabel_5": 79,
    "PartyIdentifierLabel_6": 104,
    "PartyInfoLabel": 58,
    "PartyNamelabel": 59,
    "PartyNamelabel_1": 65,
    "PartyNamelabel_10": 105,
    "PartyNamelabel_2": 71,
    "PartyNamelabel_3": 69,
    "PartyNamelabel_4": 72,
    "PartyNamelabel_5": 70,
    "PartyNamelabel_6": 66,
    "PartyNamelabel_7": 64,
    "PartyNamelabel_8": 78,
    "PartyNamelabel_9": 96,
    "PartyNavigator": 5,
    "PartySearchButton": 82,
    "PartySearchID": 84,
    "PartySpecBackArrow": 57,
    "PartySpecification": 56,
    "PartyTitle": 81,
    "Product": 9,
    "ProductBackArrow": 12,
    "ProductButton": 109,
    "ProductCreator": 113,
    "ProductGallery": 14,
    "ProductInfoLabel": 77,
    "ProductNavigator": 7,
    "ProductSearchButton": 11,
    "ProductSearchID": 13,
    "ProductSpecBackArrow": 76,
    "ProductSpecification": 75,
    "ProductTitle": 10,
    "Separator2": 20,
    "Separator2_1": 91,
    "Separator2_2": 33,
    "Separator2_3": 52,
    "Separator3": 103,
    "Subtitle2": 19,
    "Subtitle2_1": 90,
    "Subtitle2_2": 32,
    "Subtitle2_3": 51,
    "Subtitle3": 102,
    "Title2": 17,
    "Title2_1": 88,
    "Title2_2": 30,
    "Title2_3": 49,
    "Title3": 100,
    "TypeInput": 35,
    "TypeLabel": 34
  },
  "FunctionParamsInvariantScripts": {},
  "FunctionParamsInvariantScriptsOnInstances": {},
  "HeaderLastSavedDateTimeUTC": "07/12/2022 15:25:28",
  "IsLegacyComponentAllowGlobalScopeCase": false,
  "LocalConnectionIDReferences": {},
  "LocalDatabaseReferencesAsEmpty": false,
  "LocalResourceFileNames": {},
  "LocalResourceRootPaths": {},
  "OrderComponentMetadata": {},
  "OrderComponentTemplate": {},
  "OrderDataSource": {
    "CustomGallerySample": 0
  },
  "OrderGroupControls": {},
  "OrderPcfTemplate": {},
  "OrderTemplate": {},
  "OrderXMLTemplate": {
    "button": 1,
    "gallery": 4,
    "icon": 2,
    "image": 5,
    "label": 0,
    "rectangle": 6,
    "text": 3
  },
  "PublishOrderIndices": {
    "App": 0,
    "BeneficiaryInput": 38,
    "BeneficiaryLabel": 37,
    "Claim": 0,
    "ClaimBackArrow": 54,
    "ClaimButton": 9,
    "ClaimCreator": 0,
    "ClaimGallery": 56,
    "ClaimInfoLabel": 88,
    "ClaimNavigator": 4,
    "ClaimSeachtButton": 53,
    "ClaimSearchID": 55,
    "ClaimSpecBackArrow": 87,
    "ClaimSpecification": 0,
    "ClaimTitle": 52,
    "Contract": 0,
    "ContractBackArrow": 24,
    "ContractButton": 7,
    "ContractCreator": 0,
    "ContractGallery": 26,
    "ContractInfoLabel": 71,
    "ContractNavigator": 2,
    "ContractSearchButton": 23,
    "ContractSearchID": 25,
    "ContractsInput": 64,
    "ContractsLabel": 63,
    "ContractSpecBackArrow": 70,
    "ContractSpecification": 0,
    "ContractTitle": 22,
    "EntryScreen": 0,
    "EntryTitle": 0,
    "EntryTitle2": 5,
    "Gallery3": 91,
    "galleryTemplate2": 45,
    "galleryTemplate2_1": 15,
    "galleryTemplate2_2": 27,
    "galleryTemplate2_3": 57,
    "galleryTemplate3": 92,
    "HolderInput": 36,
    "HolderLabel": 35,
    "Image2": 46,
    "Image2_1": 16,
    "Image2_2": 28,
    "Image2_3": 58,
    "Image3": 93,
    "LoadMoreClaims": 65,
    "LoadMoreContracts": 39,
    "LoadMoreParties": 21,
    "LoadMoreProducts": 51,
    "NextArrow2": 48,
    "NextArrow2_1": 18,
    "NextArrow2_2": 30,
    "NextArrow2_3": 60,
    "NextArrow3": 95,
    "Party": 0,
    "PartyBackArrow": 12,
    "PartyButton": 6,
    "PartyCreator": 0,
    "PartyGallery": 14,
    "PartyIdentifierLabel": 69,
    "PartyIdentifierLabel_1": 75,
    "PartyIdentifierLabel_2": 81,
    "PartyIdentifierLabel_3": 82,
    "PartyIdentifierLabel_4": 76,
    "PartyIdentifierLabel_5": 86,
    "PartyIdentifierLabel_6": 98,
    "PartyInfoLabel": 67,
    "PartyNamelabel": 68,
    "PartyNamelabel_1": 73,
    "PartyNamelabel_10": 89,
    "PartyNamelabel_2": 79,
    "PartyNamelabel_3": 77,
    "PartyNamelabel_4": 80,
    "PartyNamelabel_5": 78,
    "PartyNamelabel_6": 74,
    "PartyNamelabel_7": 72,
    "PartyNamelabel_8": 85,
    "PartyNamelabel_9": 90,
    "PartyNavigator": 1,
    "PartySearchButton": 11,
    "PartySearchID": 13,
    "PartySpecBackArrow": 66,
    "PartySpecification": 0,
    "PartyTitle": 10,
    "Product": 0,
    "ProductBackArrow": 42,
    "ProductButton": 8,
    "ProductCreator": 0,
    "ProductGallery": 44,
    "ProductInfoLabel": 84,
    "ProductNavigator": 3,
    "ProductSearchButton": 41,
    "ProductSearchID": 43,
    "ProductSpecBackArrow": 83,
    "ProductSpecification": 0,
    "ProductTitle": 40,
    "Separator2": 50,
    "Separator2_1": 20,
    "Separator2_2": 32,
    "Separator2_3": 62,
    "Separator3": 97,
    "Subtitle2": 49,
    "Subtitle2_1": 19,
    "Subtitle2_2": 31,
    "Subtitle2_3": 61,
    "Subtitle3": 96,
    "Title2": 47,
    "Title2_1": 17,
    "Title2_2": 29,
    "Title2_3": 59,
    "Title3": 94,
    "TypeInput": 34,
    "TypeLabel": 33
  },
  "ResourcesJsonIndices": {
    "Image-SampleImage": 0
  },
  "RuleScreenIdWithoutScreen": {},
  "TemplateVersions": {},
  "VolatileProperties": {
    "AnalysisLoadTime": 0.7272667,
    "ControlCount": {
      "button": 12,
      "gallery": 5,
      "galleryTemplate": 5,
      "icon": 17,
      "image": 5,
      "label": 42,
      "rectangle": 5,
      "screen": 9,
      "text": 8
    },
    "DeserializationLoadTime": 1.619352,
    "ErrorCount": 0
  },
  "WasLocalDatabaseReferencesEmpty": true
}